README.md
setup.cfg
setup.py
uaddressformat/__init__.py
uaddressformat.egg-info/PKG-INFO
uaddressformat.egg-info/SOURCES.txt
uaddressformat.egg-info/dependency_links.txt
uaddressformat.egg-info/top_level.txt