Metadata-Version: 2.1
Name: uaddressformat
Version: 1.0.2
Summary: Library for uaddress package. Format types addresses
Home-page: https://github.com/RapidappsIT/uaddressformat
Author: Evgen Kytonin
Author-email: killfess@gmail.com
License: MIT
Keywords: module,parse,uaddress
Platform: UNKNOWN
